setup.py
av_distributions/Binomialdistribution.py
av_distributions/Gaussiandistribution.py
av_distributions/Generaldistribution.py
av_distributions/__init__.py
av_distributions.egg-info/PKG-INFO
av_distributions.egg-info/SOURCES.txt
av_distributions.egg-info/dependency_links.txt
av_distributions.egg-info/not-zip-safe
av_distributions.egg-info/top_level.txt